{"version":1,"resource":"file:///home/roman/.config/hypr/themes/catppuccin/scripts/weather.sh","entries":[{"id":"ZAP4.sh","timestamp":1719424731780},{"id":"KuI4.sh","timestamp":1719424815395},{"id":"GMpe.sh","timestamp":1719424907879},{"id":"zSjQ.sh","timestamp":1719424966790},{"id":"jkbT.sh","source":"undoRedo.source","timestamp":1719425022332},{"id":"jDJd.sh","timestamp":1719425096949},{"id":"O75l.sh","timestamp":1719425171574},{"id":"X5Mb.sh","source":"undoRedo.source","timestamp":1719425197318}]}